df_to_azure/__init__.py
df_to_azure/adf.py
df_to_azure/db.py
df_to_azure/exceptions.py
df_to_azure/export.py
df_to_azure/settings.py
df_to_azure/utils.py
df_to_azure-1.0.2.dist-info/LICENSE
df_to_azure-1.0.2.dist-info/METADATA
df_to_azure-1.0.2.dist-info/WHEEL
df_to_azure-1.0.2.dist-info/top_level.txt
df_to_azure-1.0.2.dist-info/RECORD
