Metadata-Version: 2.2
Name: df_to_azure
Version: 1.0.2
Summary: Automatically write pandas DataFrames to SQL by creating pipelines in Azure Data Factory with copy activity from blob to SQL
Home-page: https://github.com/zypp-io/df_to_azure
Author: Zypp
Author-email: hello@zypp.io
Project-URL: Bug Tracker, https://github.com/zypp-io/df_to_azure/issues
Project-URL: Source, https://github.com/zypp-io/df_to_azure
Keywords: python,azure,data-warehouse,sql,blob
Classifier: Programming Language :: Python :: 3
Classifier: License :: OSI Approved :: MIT License
Classifier: Operating System :: OS Independent
Requires-Python: >=3.9
License-File: LICENSE
Requires-Dist: azure-identity>=1.12.0
Requires-Dist: azure-mgmt-datafactory>=7.1.0
Requires-Dist: azure-mgmt-resource>=23.1.1
Requires-Dist: azure-storage-blob>=12.20.0
Requires-Dist: pandas>=2.2.2
Requires-Dist: pyarrow>=16.1.0
Requires-Dist: pyodbc>=5.1.0
Requires-Dist: sqlalchemy>=2.0.30
